domain_repository/__init__.py
domain_repository/operational/__init__.py
domain_repository/operational/component.py
domain_repository/operational/expectation.py
domain_repository/operational/protocol.py
domain_repository/operational/workflow.py
domain_repository-0.1.0.dist-info/METADATA
domain_repository-0.1.0.dist-info/WHEEL
domain_repository-0.1.0.dist-info/RECORD
