Metadata-Version: 2.1
Name: domain-repository
Version: 0.1.0
Summary: Domain metamodels for operational excellence platform.
License: MIT
Author: joneill116
Author-email: your-email@example.com
Requires-Python: >=3.8,<4.0
Classifier: License :: OSI Approved :: MIT License
Classifier: Programming Language :: Python :: 3
Classifier: Programming Language :: Python :: 3.8
Classifier: Programming Language :: Python :: 3.9
Classifier: Programming Language :: Python :: 3.10
Classifier: Programming Language :: Python :: 3.11
Classifier: Programming Language :: Python :: 3.12
Requires-Dist: pydantic (>=1.10,<3.0)
